deepseek_agent-0.6.6.dist-info/licenses/LICENSE
deepseek_cli/__init__.py
deepseek_cli/__main__.py
deepseek_cli/agent.py
deepseek_cli/chat.py
deepseek_cli/cli.py
deepseek_cli/completions.py
deepseek_cli/config.py
deepseek_cli/constants.py
deepseek_cli/embeddings.py
deepseek_cli/models.py
deepseek_cli/streaming.py
deepseek_cli/testing.py
deepseek_agent-0.6.6.dist-info/METADATA
deepseek_agent-0.6.6.dist-info/WHEEL
deepseek_agent-0.6.6.dist-info/entry_points.txt
deepseek_agent-0.6.6.dist-info/top_level.txt
deepseek_agent-0.6.6.dist-info/RECORD
