Metadata-Version: 2.4
Name: deepseek_agent
Version: 0.6.6
Summary: Developer-focused DeepSeek command line tools
Author: DeepSeek CLI Maintainers
License-Expression: MIT
Project-URL: Homepage, https://github.com/deepseek/deepseek-cli
Requires-Python: >=3.9
License-File: LICENSE
Requires-Dist: openai>=1.13.3
Requires-Dist: packaging>=24.0
Requires-Dist: rich>=13.7.0
Requires-Dist: prompt-toolkit>=3.0.43
Requires-Dist: pytest>=8.2.0
Requires-Dist: pytest-mock>=3.14.0
Dynamic: license-file
